ptc2_0_1/__init__.py
ptc2_0_1/condition.py
ptc2_0_1/database.py
ptc2_0_1/datatypes.py
ptc2_0_1/interaction.py
ptc2_0_1/storage.py
ptc2_0_1/database_lib/mysql.py
ptc2_0_1/database_lib/postgresql.py
ptc2_0_1/database_lib/sqlite.py
pytopconnect/__init__.py
pytopconnect/condition.py
pytopconnect/database.py
pytopconnect/datatypes.py
pytopconnect/interaction.py
pytopconnect/storage.py
pytopconnect/database_lib/mysql.py
pytopconnect/database_lib/postgresql.py
pytopconnect/database_lib/sqlite.py
pytopconnect-1.1.5.1.dist-info/METADATA
pytopconnect-1.1.5.1.dist-info/WHEEL
pytopconnect-1.1.5.1.dist-info/top_level.txt
pytopconnect-1.1.5.1.dist-info/RECORD
