Metadata-Version: 2.1
Name: pytopconnect
Version: 1.1.5.1
Summary: The library is designed to interact with various databases
Home-page: https://github.com/npawcompany/pytopconnect-1.1.x
Author: Apinyan Gor
Author-email: poenixgfx102938@gmail.com
Classifier: Programming Language :: Python :: 3.6
Classifier: Programming Language :: Python :: 3.7
Classifier: Programming Language :: Python :: 3.8
Classifier: Programming Language :: Python :: 3.9
Classifier: Programming Language :: Python :: 3.10
Classifier: Programming Language :: Python :: 3.11
Classifier: Programming Language :: Python :: 3.12
Classifier: License :: OSI Approved :: MIT License
Classifier: Operating System :: OS Independent
Requires-Python: >=3.6
Requires-Dist: pymysql>=1.0
Requires-Dist: psycopg2>=2.8
Requires-Dist: numpy>=1.20
Requires-Dist: pandas>=1.2
Requires-Dist: tqdm>=4.60
Requires-Dist: fuzzywuzzy>=0.18
